kdslibs/__init__.py
kdslibs/data.py
kdslibs/resources/data.py
kdslibs-0.0.33.dist-info/LICENSE
kdslibs-0.0.33.dist-info/METADATA
kdslibs-0.0.33.dist-info/WHEEL
kdslibs-0.0.33.dist-info/top_level.txt
kdslibs-0.0.33.dist-info/RECORD
